halt/__init__.py
halt/halt.py
halt/util.py
halt-0.1.1.dist-info/DESCRIPTION.rst
halt-0.1.1.dist-info/METADATA
halt-0.1.1.dist-info/RECORD
halt-0.1.1.dist-info/WHEEL
halt-0.1.1.dist-info/metadata.json
halt-0.1.1.dist-info/top_level.txt
