Metadata-Version: 2.0
Name: halt
Version: 0.1.1
Summary: very light wieght db helper for sqlite, has some small mashconfig magic
Home-page: UNKNOWN
Author: timothy eichler
Author-email: tim_eichler@hotmail.com
License: BSD
Keywords: sqlite db helper lightweight sql magic
Platform: UNKNOWN
Classifier: Development Status :: 3 - Alpha
Classifier: Intended Audience :: Developers
Classifier: License :: OSI Approved :: BSD License
Classifier: Programming Language :: Python :: 3
